zpp_color/__init__.py
zpp_color/color.py
zpp_color-1.0.4.dist-info/LICENSE
zpp_color-1.0.4.dist-info/METADATA
zpp_color-1.0.4.dist-info/WHEEL
zpp_color-1.0.4.dist-info/top_level.txt
zpp_color-1.0.4.dist-info/RECORD
