Metadata-Version: 2.1
Name: zpp_color
Version: 1.0.4
Summary: Colorisation de texte dans un terminal
Home-page: https://github.com/ZephyrOff/zpp_color
Author: 
License: MIT License
Project-URL: Documentation, https://github.com/ZephyrOff/zpp_color
Platform: ALL
License-File: LICENSE
